{
"type": "FeatureCollection",
"name": "QR code points",
"crs": { "type": "name", "properties": { "name": "urn:ogc:def:crs:OGC:1.3:CRS84" } },
"features": [
{ "type": "Feature", "properties": { "Name": "1","type":"building", "description": "", "timestamp": null, "begin": null, "end": null, "altitudeMode": null, "tessellate": -1, "extrude": 0, "visibility": -1, "drawOrder": null, "icon": null, "folders": "QR code points", "altitude": 0.0, "alt_mode": "", "time_begin": "", "time_end": "", "time_when": "" }, "geometry": { "type": "Point", "coordinates": [ 76.682921381742801, 11.401583405325299, 0.0 ] } },
{ "type": "Feature", "properties": { "Name": "2","type":"amenity", "description": "", "timestamp": null, "begin": null, "end": null, "altitudeMode": null, "tessellate": -1, "extrude": 0, "visibility": -1, "drawOrder": null, "icon": null, "folders": "QR code points", "altitude": 0.0, "alt_mode": "", "time_begin": "", "time_end": "", "time_when": "" }, "geometry": { "type": "Point", "coordinates": [ 76.683730423760906, 11.401736541896099, 0.0 ] } },
{ "type": "Feature", "properties": { "Name": "3","type":"amenity", "description": "", "timestamp": null, "begin": null, "end": null, "altitudeMode": null, "tessellate": -1, "extrude": 0, "visibility": -1, "drawOrder": null, "icon": null, "folders": "QR code points", "altitude": 0.0, "alt_mode": "", "time_begin": "", "time_end": "", "time_when": "" }, "geometry": { "type": "Point", "coordinates": [ 76.684149520445402, 11.402227027159199, 0.0 ] } },
{ "type": "Feature", "properties": { "Name": "4","type":"amenity", "description": "", "timestamp": null, "begin": null, "end": null, "altitudeMode": null, "tessellate": -1, "extrude": 0, "visibility": -1, "drawOrder": null, "icon": null, "folders": "QR code points", "altitude": 0.0, "alt_mode": "", "time_begin": "", "time_end": "", "time_when": "" }, "geometry": { "type": "Point", "coordinates": [ 76.683879759154706, 11.4006193446452, 0.0 ] } },
{ "type": "Feature", "properties": { "Name": "5","type":"amenity", "description": "", "timestamp": null, "begin": null, "end": null, "altitudeMode": null, "tessellate": -1, "extrude": 0, "visibility": -1, "drawOrder": null, "icon": null, "folders": "QR code points", "altitude": 0.0, "alt_mode": "", "time_begin": "", "time_end": "", "time_when": "" }, "geometry": { "type": "Point", "coordinates": [ 76.683526335218801, 11.4008931541007, 0.0 ] } },
{ "type": "Feature", "properties": { "Name": "6","type":"amenity", "description": "", "timestamp": null, "begin": null, "end": null, "altitudeMode": null, "tessellate": -1, "extrude": 0, "visibility": -1, "drawOrder": null, "icon": null, "folders": "QR code points", "altitude": 0.0, "alt_mode": "", "time_begin": "", "time_end": "", "time_when": "" }, "geometry": { "type": "Point", "coordinates": [ 76.682355900888197, 11.3995486737674, 0.0 ] } }
]
}
